langchain_nexa_ai/__init__.py
langchain_nexa_ai/llms.py
langchain_nexa_ai/py.typed
langchain_nexa_ai-0.1.5.dist-info/LICENSE
langchain_nexa_ai-0.1.5.dist-info/METADATA
langchain_nexa_ai-0.1.5.dist-info/WHEEL
langchain_nexa_ai-0.1.5.dist-info/RECORD
