Metadata-Version: 2.1
Name: langchain-nexa-ai
Version: 0.1.5
Summary: An integration package connecting NexaAI and LangChain
Home-page: https://github.com/langchain-ai/langchain
License: MIT
Author: Ethan Wang
Author-email: ethan@nexa4ai.com
Requires-Python: >=3.8.1,<4.0
Classifier: License :: OSI Approved :: MIT License
Classifier: Programming Language :: Python :: 3
Classifier: Programming Language :: Python :: 3.9
Classifier: Programming Language :: Python :: 3.10
Classifier: Programming Language :: Python :: 3.11
Classifier: Programming Language :: Python :: 3.12
Requires-Dist: langchain-core (>=0.2.0,<0.3.0)
Project-URL: Repository, https://github.com/langchain-ai/langchain
Project-URL: Source Code, https://github.com/langchain-ai/langchain/tree/master/libs/partners/nexa-ai
